{
  "@type" : "TEMPLATE",
  "uid" : "60b0aeff-a9ab-43bb-af0a-5113b90a8bd7",
  "description" : {
    "@type" : "RESOURCE_DESCRIPTION",
    "originalAuthor" : {
      "date" : "2020-10-02"
    },
    "otherContributors" : [ ],
    "lifecycleState" : {
      "codeString" : "unmanaged"
    },
    "ipAcknowledgements" : { },
    "references" : { },
    "conversionDetails" : { },
    "otherDetails" : {
      "licence" : "This work is licensed under the Creative Commons Attribution-ShareAlike 4.0 International License. To view a copy of this license, visit http://creativecommons.org/licenses/by-sa/4.0/.",
      "custodian_organisation" : "openEHR Foundation",
      "original_namespace" : "org.openehr",
      "original_publisher" : "openEHR Foundation",
      "custodian_namespace" : "org.openehr",
      "MD5-CAM-1.0.1" : "ef5993970e8bf229d6ec98eb74987fb6",
      "PARENT:MD5-CAM-1.0.1" : "4BF04E7D09B866397CA12BAFED2BC216"
    },
    "details" : {
      "de" : {
        "@type" : "RESOURCE_DESCRIPTION_ITEM",
        "language" : {
          "terminologyId" : {
            "value" : "ISO_639-1"
          },
          "codeString" : "de"
        },
        "keywords" : [ ],
        "originalResourceUri" : { },
        "otherDetails" : { }
      },
      "fi" : {
        "@type" : "RESOURCE_DESCRIPTION_ITEM",
        "language" : {
          "terminologyId" : {
            "value" : "ISO_639-1"
          },
          "codeString" : "fi"
        },
        "keywords" : [ ],
        "originalResourceUri" : { },
        "otherDetails" : { }
      },
      "sv" : {
        "@type" : "RESOURCE_DESCRIPTION_ITEM",
        "language" : {
          "terminologyId" : {
            "value" : "ISO_639-1"
          },
          "codeString" : "sv"
        },
        "keywords" : [ ],
        "originalResourceUri" : { },
        "otherDetails" : { }
      },
      "ko" : {
        "@type" : "RESOURCE_DESCRIPTION_ITEM",
        "language" : {
          "terminologyId" : {
            "value" : "ISO_639-1"
          },
          "codeString" : "ko"
        },
        "keywords" : [ ],
        "originalResourceUri" : { },
        "otherDetails" : { }
      },
      "nb" : {
        "@type" : "RESOURCE_DESCRIPTION_ITEM",
        "language" : {
          "terminologyId" : {
            "value" : "ISO_639-1"
          },
          "codeString" : "nb"
        },
        "keywords" : [ ],
        "originalResourceUri" : { },
        "otherDetails" : { }
      },
      "es-ar" : {
        "@type" : "RESOURCE_DESCRIPTION_ITEM",
        "language" : {
          "terminologyId" : {
            "value" : "ISO_639-1"
          },
          "codeString" : "es-ar"
        },
        "keywords" : [ ],
        "originalResourceUri" : { },
        "otherDetails" : { }
      },
      "pt-br" : {
        "@type" : "RESOURCE_DESCRIPTION_ITEM",
        "language" : {
          "terminologyId" : {
            "value" : "ISO_639-1"
          },
          "codeString" : "pt-br"
        },
        "keywords" : [ ],
        "originalResourceUri" : { },
        "otherDetails" : { }
      },
      "en" : {
        "@type" : "RESOURCE_DESCRIPTION_ITEM",
        "language" : {
          "terminologyId" : {
            "value" : "ISO_639-1"
          },
          "codeString" : "en"
        },
        "keywords" : [ ],
        "originalResourceUri" : { },
        "otherDetails" : { }
      },
      "ar-sy" : {
        "@type" : "RESOURCE_DESCRIPTION_ITEM",
        "language" : {
          "terminologyId" : {
            "value" : "ISO_639-1"
          },
          "codeString" : "ar-sy"
        },
        "keywords" : [ ],
        "originalResourceUri" : { },
        "otherDetails" : { }
      },
      "it" : {
        "@type" : "RESOURCE_DESCRIPTION_ITEM",
        "language" : {
          "terminologyId" : {
            "value" : "ISO_639-1"
          },
          "codeString" : "it"
        },
        "keywords" : [ ],
        "originalResourceUri" : { },
        "otherDetails" : { }
      },
      "nl" : {
        "@type" : "RESOURCE_DESCRIPTION_ITEM",
        "language" : {
          "terminologyId" : {
            "value" : "ISO_639-1"
          },
          "codeString" : "nl"
        },
        "keywords" : [ ],
        "originalResourceUri" : { },
        "otherDetails" : { }
      },
      "es" : {
        "@type" : "RESOURCE_DESCRIPTION_ITEM",
        "language" : {
          "terminologyId" : {
            "value" : "ISO_639-1"
          },
          "codeString" : "es"
        },
        "keywords" : [ ],
        "originalResourceUri" : { },
        "otherDetails" : { }
      }
    }
  },
  "parentArchetypeId" : "openEHR-EHR-EVALUATION.problem_diagnosis.v1",
  "differential" : true,
  "archetypeId" : {
    "@type" : "ARCHETYPE_HRID",
    "value" : "openEHR-EHR-EVALUATION.problemdiagnosis.v1"
  },
  "definition" : {
    "@type" : "C_COMPLEX_OBJECT",
    "rmTypeName" : "EVALUATION",
    "nodeId" : "at0000.1",
    "attributes" : [ {
      "@type" : "C_ATTRIBUTE",
      "rmAttributeName" : "data",
      "children" : [ {
        "@type" : "C_COMPLEX_OBJECT",
        "rmTypeName" : "ITEM_TREE",
        "nodeId" : "at0001",
        "attributes" : [ {
          "@type" : "C_ATTRIBUTE",
          "rmAttributeName" : "items",
          "children" : [ {
            "@type" : "C_COMPLEX_OBJECT",
            "rmTypeName" : "ELEMENT",
            "occurrences" : "0..0",
            "nodeId" : "at0009.1",
            "attributes" : [ ],
            "attributeTuples" : [ ]
          }, {
            "@type" : "C_COMPLEX_OBJECT",
            "rmTypeName" : "ELEMENT",
            "occurrences" : "0..0",
            "nodeId" : "at0012.1",
            "attributes" : [ ],
            "attributeTuples" : [ ]
          }, {
            "@type" : "C_COMPLEX_OBJECT",
            "rmTypeName" : "ELEMENT",
            "occurrences" : "0..0",
            "nodeId" : "at0077.1",
            "attributes" : [ {
              "@type" : "C_ATTRIBUTE",
              "rmAttributeName" : "value",
              "children" : [ {
                "@type" : "C_COMPLEX_OBJECT",
                "rmTypeName" : "DV_DATE_TIME",
                "attributes" : [ {
                  "@type" : "C_ATTRIBUTE",
                  "rmAttributeName" : "value",
                  "children" : [ {
                    "@type" : "C_DATE_TIME",
                    "rmTypeName" : "DATE_TIME",
                    "constraint" : [ ]
                  } ]
                } ],
                "attributeTuples" : [ ]
              } ]
            } ],
            "attributeTuples" : [ ]
          }, {
            "@type" : "C_COMPLEX_OBJECT",
            "rmTypeName" : "ELEMENT",
            "occurrences" : "0..0",
            "nodeId" : "at0003.1",
            "attributes" : [ {
              "@type" : "C_ATTRIBUTE",
              "rmAttributeName" : "value",
              "children" : [ {
                "@type" : "C_COMPLEX_OBJECT",
                "rmTypeName" : "DV_DATE_TIME",
                "attributes" : [ {
                  "@type" : "C_ATTRIBUTE",
                  "rmAttributeName" : "value",
                  "children" : [ {
                    "@type" : "C_DATE_TIME",
                    "rmTypeName" : "DATE_TIME",
                    "constraint" : [ ]
                  } ]
                } ],
                "attributeTuples" : [ ]
              } ]
            } ],
            "attributeTuples" : [ ]
          }, {
            "@type" : "C_COMPLEX_OBJECT",
            "rmTypeName" : "ELEMENT",
            "occurrences" : "0..0",
            "nodeId" : "at0005.1",
            "attributes" : [ {
              "@type" : "C_ATTRIBUTE",
              "rmAttributeName" : "value",
              "children" : [ {
                "@type" : "C_COMPLEX_OBJECT",
                "rmTypeName" : "DV_CODED_TEXT",
                "attributes" : [ {
                  "@type" : "C_ATTRIBUTE",
                  "rmAttributeName" : "defining_code",
                  "children" : [ {
                    "@type" : "C_TERMINOLOGY_CODE",
                    "rmTypeName" : "TERMINOLOGY_CODE",
                    "occurrences" : "1..1",
                    "terminologyId" : {
                      "value" : "local"
                    },
                    "constraint" : [ "ac0.1" ],
                    "selectedTerminologies" : [ ]
                  } ]
                } ],
                "attributeTuples" : [ ]
              }, {
                "@type" : "C_COMPLEX_OBJECT",
                "rmTypeName" : "DV_TEXT",
                "attributes" : [ ],
                "attributeTuples" : [ ]
              } ]
            } ],
            "attributeTuples" : [ ]
          }, {
            "@type" : "C_COMPLEX_OBJECT",
            "rmTypeName" : "ELEMENT",
            "occurrences" : "0..0",
            "nodeId" : "at0072.1",
            "attributes" : [ ],
            "attributeTuples" : [ ]
          }, {
            "@type" : "C_COMPLEX_OBJECT",
            "rmTypeName" : "ELEMENT",
            "occurrences" : "0..0",
            "nodeId" : "at0030.1",
            "attributes" : [ {
              "@type" : "C_ATTRIBUTE",
              "rmAttributeName" : "value",
              "children" : [ {
                "@type" : "C_COMPLEX_OBJECT",
                "rmTypeName" : "DV_DATE_TIME",
                "attributes" : [ {
                  "@type" : "C_ATTRIBUTE",
                  "rmAttributeName" : "value",
                  "children" : [ {
                    "@type" : "C_DATE_TIME",
                    "rmTypeName" : "DATE_TIME",
                    "constraint" : [ ]
                  } ]
                } ],
                "attributeTuples" : [ ]
              } ]
            } ],
            "attributeTuples" : [ ]
          }, {
            "@type" : "C_COMPLEX_OBJECT",
            "rmTypeName" : "ELEMENT",
            "occurrences" : "0..0",
            "nodeId" : "at0073.1",
            "attributes" : [ {
              "@type" : "C_ATTRIBUTE",
              "rmAttributeName" : "value",
              "children" : [ {
                "@type" : "C_COMPLEX_OBJECT",
                "rmTypeName" : "DV_CODED_TEXT",
                "attributes" : [ {
                  "@type" : "C_ATTRIBUTE",
                  "rmAttributeName" : "defining_code",
                  "children" : [ {
                    "@type" : "C_TERMINOLOGY_CODE",
                    "rmTypeName" : "TERMINOLOGY_CODE",
                    "occurrences" : "1..1",
                    "terminologyId" : {
                      "value" : "local"
                    },
                    "constraint" : [ "ac0.3" ],
                    "selectedTerminologies" : [ ]
                  } ]
                } ],
                "attributeTuples" : [ ]
              }, {
                "@type" : "C_COMPLEX_OBJECT",
                "rmTypeName" : "DV_TEXT",
                "attributes" : [ ],
                "attributeTuples" : [ ]
              } ]
            } ],
            "attributeTuples" : [ ]
          }, {
            "@type" : "C_COMPLEX_OBJECT",
            "rmTypeName" : "ELEMENT",
            "occurrences" : "0..0",
            "nodeId" : "at0069.1",
            "attributes" : [ ],
            "attributeTuples" : [ ]
          } ]
        } ],
        "attributeTuples" : [ ]
      } ]
    } ],
    "attributeTuples" : [ ]
  },
  "terminology" : {
    "@type" : "ARCHETYPE_TERMINOLOGY",
    "conceptCode" : "at0000",
    "termDefinitions" : {
      "es" : {
        "ac0.1" : {
          "@type" : "ARCHETYPE_TERM",
          "text" : "*(Synthesized) (en)",
          "code" : "ac0.1",
          "description" : ""
        },
        "ac0.3" : {
          "@type" : "ARCHETYPE_TERM",
          "text" : "*(Synthesized) (en)",
          "code" : "ac0.3",
          "description" : ""
        }
      },
      "es-ar" : {
        "ac0.1" : {
          "@type" : "ARCHETYPE_TERM",
          "text" : "*(Synthesized) (en)",
          "code" : "ac0.1",
          "description" : ""
        },
        "ac0.3" : {
          "@type" : "ARCHETYPE_TERM",
          "text" : "*(Synthesized) (en)",
          "code" : "ac0.3",
          "description" : ""
        }
      },
      "de" : {
        "ac0.1" : {
          "@type" : "ARCHETYPE_TERM",
          "text" : "*(Synthesized) (en)",
          "code" : "ac0.1",
          "description" : ""
        },
        "ac0.3" : {
          "@type" : "ARCHETYPE_TERM",
          "text" : "*(Synthesized) (en)",
          "code" : "ac0.3",
          "description" : ""
        }
      },
      "en" : {
        "ac0.1" : {
          "@type" : "ARCHETYPE_TERM",
          "text" : "(Synthesized)",
          "code" : "ac0.1",
          "description" : ""
        },
        "ac0.3" : {
          "@type" : "ARCHETYPE_TERM",
          "text" : "(Synthesized)",
          "code" : "ac0.3",
          "description" : ""
        }
      },
      "ar-sy" : {
        "ac0.1" : {
          "@type" : "ARCHETYPE_TERM",
          "text" : "*(Synthesized) (en)",
          "code" : "ac0.1",
          "description" : ""
        },
        "ac0.3" : {
          "@type" : "ARCHETYPE_TERM",
          "text" : "*(Synthesized) (en)",
          "code" : "ac0.3",
          "description" : ""
        }
      },
      "pt-br" : {
        "ac0.1" : {
          "@type" : "ARCHETYPE_TERM",
          "text" : "*(Synthesized) (en)",
          "code" : "ac0.1",
          "description" : ""
        },
        "ac0.3" : {
          "@type" : "ARCHETYPE_TERM",
          "text" : "*(Synthesized) (en)",
          "code" : "ac0.3",
          "description" : ""
        }
      },
      "nb" : {
        "ac0.1" : {
          "@type" : "ARCHETYPE_TERM",
          "text" : "*(Synthesized) (en)",
          "code" : "ac0.1",
          "description" : ""
        },
        "ac0.3" : {
          "@type" : "ARCHETYPE_TERM",
          "text" : "*(Synthesized) (en)",
          "code" : "ac0.3",
          "description" : ""
        }
      },
      "sv" : {
        "ac0.1" : {
          "@type" : "ARCHETYPE_TERM",
          "text" : "*(Synthesized) (en)",
          "code" : "ac0.1",
          "description" : ""
        },
        "ac0.3" : {
          "@type" : "ARCHETYPE_TERM",
          "text" : "*(Synthesized) (en)",
          "code" : "ac0.3",
          "description" : ""
        }
      },
      "ko" : {
        "ac0.1" : {
          "@type" : "ARCHETYPE_TERM",
          "text" : "*(Synthesized) (en)",
          "code" : "ac0.1",
          "description" : ""
        },
        "ac0.3" : {
          "@type" : "ARCHETYPE_TERM",
          "text" : "*(Synthesized) (en)",
          "code" : "ac0.3",
          "description" : ""
        }
      },
      "fi" : {
        "ac0.1" : {
          "@type" : "ARCHETYPE_TERM",
          "text" : "*(Synthesized) (en)",
          "code" : "ac0.1",
          "description" : ""
        },
        "ac0.3" : {
          "@type" : "ARCHETYPE_TERM",
          "text" : "*(Synthesized) (en)",
          "code" : "ac0.3",
          "description" : ""
        }
      },
      "it" : {
        "ac0.1" : {
          "@type" : "ARCHETYPE_TERM",
          "text" : "*(Synthesized) (en)",
          "code" : "ac0.1",
          "description" : ""
        },
        "ac0.3" : {
          "@type" : "ARCHETYPE_TERM",
          "text" : "*(Synthesized) (en)",
          "code" : "ac0.3",
          "description" : ""
        }
      },
      "nl" : {
        "ac0.1" : {
          "@type" : "ARCHETYPE_TERM",
          "text" : "*(Synthesized) (en)",
          "code" : "ac0.1",
          "description" : ""
        },
        "ac0.3" : {
          "@type" : "ARCHETYPE_TERM",
          "text" : "*(Synthesized) (en)",
          "code" : "ac0.3",
          "description" : ""
        }
      }
    },
    "termBindings" : { },
    "terminologyExtracts" : { },
    "valueSets" : {
      "ac0.1" : {
        "@type" : "VALUE_SET",
        "id" : "ac0.1",
        "members" : [ "at0047", "at0048", "at0049" ]
      },
      "ac0.2" : {
        "@type" : "VALUE_SET",
        "id" : "ac0.2",
        "members" : [ "at0074", "at0075", "at0076" ]
      },
      "ac0.3" : {
        "@type" : "VALUE_SET",
        "id" : "ac0.3",
        "members" : [ "at0074", "at0075", "at0076" ]
      }
    }
  },
  "adlVersion" : "1.4",
  "buildUid" : "97a0399c-843d-3c83-af16-29fe0b15c5a7",
  "rmName" : "openehr",
  "rmRelease" : "1.0.3",
  "generated" : true,
  "templateId" : "TMP Problem/Diagnosis",
  "otherMetaData" : { },
  "templateOverlays" : [ ],
  "originalLanguage" : {
    "terminologyId" : {
      "value" : "ISO_639-1"
    },
    "codeString" : "en"
  },
  "translations" : [ {
    "@type" : "TRANSLATION_DETAILS",
    "language" : {
      "terminologyId" : {
        "value" : "ISO_639-1"
      },
      "codeString" : "de"
    },
    "author" : { },
    "otherDetails" : { }
  }, {
    "@type" : "TRANSLATION_DETAILS",
    "language" : {
      "terminologyId" : {
        "value" : "ISO_639-1"
      },
      "codeString" : "sv"
    },
    "author" : { },
    "otherDetails" : { }
  }, {
    "@type" : "TRANSLATION_DETAILS",
    "language" : {
      "terminologyId" : {
        "value" : "ISO_639-1"
      },
      "codeString" : "fi"
    },
    "author" : { },
    "otherDetails" : { }
  }, {
    "@type" : "TRANSLATION_DETAILS",
    "language" : {
      "terminologyId" : {
        "value" : "ISO_639-1"
      },
      "codeString" : "es-ar"
    },
    "author" : { },
    "otherDetails" : { }
  }, {
    "@type" : "TRANSLATION_DETAILS",
    "language" : {
      "terminologyId" : {
        "value" : "ISO_639-1"
      },
      "codeString" : "nb"
    },
    "author" : { },
    "otherDetails" : { }
  }, {
    "@type" : "TRANSLATION_DETAILS",
    "language" : {
      "terminologyId" : {
        "value" : "ISO_639-1"
      },
      "codeString" : "ko"
    },
    "author" : { },
    "otherDetails" : { }
  }, {
    "@type" : "TRANSLATION_DETAILS",
    "language" : {
      "terminologyId" : {
        "value" : "ISO_639-1"
      },
      "codeString" : "pt-br"
    },
    "author" : { },
    "otherDetails" : { }
  }, {
    "@type" : "TRANSLATION_DETAILS",
    "language" : {
      "terminologyId" : {
        "value" : "ISO_639-1"
      },
      "codeString" : "ar-sy"
    },
    "author" : { },
    "otherDetails" : { }
  }, {
    "@type" : "TRANSLATION_DETAILS",
    "language" : {
      "terminologyId" : {
        "value" : "ISO_639-1"
      },
      "codeString" : "it"
    },
    "author" : { },
    "otherDetails" : { }
  }, {
    "@type" : "TRANSLATION_DETAILS",
    "language" : {
      "terminologyId" : {
        "value" : "ISO_639-1"
      },
      "codeString" : "es"
    },
    "author" : { },
    "otherDetails" : { }
  }, {
    "@type" : "TRANSLATION_DETAILS",
    "language" : {
      "terminologyId" : {
        "value" : "ISO_639-1"
      },
      "codeString" : "nl"
    },
    "author" : { },
    "otherDetails" : { }
  } ]
}